{
  "resourceType": "CodeSystem",
  "status": "draft",
  "content": "complete",
  "name": "LibraryType",
  "id": "library-type",
  "title": "LibraryType",
  "description": "The type of knowledge asset this library contains.",
  "url": "https://fhir.kemkes.go.id/r4/CodeSystem/library-type",
  "concept": [
    {
      "code": "logic-library",
      "display": "Logic Library",
      "definition": "The resource is a shareable library of formalized knowledge."
    },
    {
      "code": "model-definition",
      "display": "Model Definition",
      "definition": "The resource is a definition of an information model."
    },
    {
      "code": "asset-collection",
      "display": "Asset Collection",
      "definition": "The resource is a collection of knowledge assets."
    },
    {
      "code": "module-definition",
      "display": "Module Definition",
      "definition": "The resource defines the dependencies, parameters, and data requirements for a particular module or evaluation context."
    }
  ],
  "meta": {
    "lastUpdated": "2020-04-09T21:10:28.568+00:00"
  },
  "extension": [
    {
      "url": "http://hl7.org/fhir/StructureDefinition/structuredefinition-wg",
      "valueCode": "cds"
    },
    {
      "url": "http://hl7.org/fhir/StructureDefinition/structuredefinition-fmm",
      "valueInteger": 2
    }
  ],
  "identifier": [
    {
      "system": "urn:ietf:rfc:3986",
      "value": "urn:oid:2.16.840.1.113883.4.642.1.1230"
    }
  ],
  "version": "1.0.0",
  "experimental": false,
  "date": "2020-04-09T21:10:28+00:00",
  "publisher": "Health Level Seven International",
  "contact": [
    {
      "telecom": [
        {
          "system": "url",
          "value": "http://hl7.org"
        },
        {
          "system": "email",
          "value": "hq@HL7.org"
        }
      ]
    }
  ],
  "copyright": "This material derives from the HL7 Terminology (THO). THO is copyright ©1989+ Health Level Seven International and is made available under the CC0 designation. For more licensing information see: https://terminology.hl7.org/license",
  "caseSensitive": true,
  "valueSet": "http://terminology.hl7.org/ValueSet/library-type",
  "count": 4
}
