{
  "resourceType": "ValueSet",
  "status": "active",
  "name": "ObservationType",
  "id": "v3-ObservationType",
  "title": "ObservationType",
  "description": "Identifies the kinds of observations that can be performed",
  "url": "https://fhir.kemkes.go.id/r4/ValueSet/v3-ObservationType",
  "language": "en",
  "identifier": [
    {
      "system": "urn:ietf:rfc:3986",
      "value": "urn:oid:2.16.840.1.113883.1.11.16226"
    }
  ],
  "version": "3.0.0",
  "experimental": false,
  "date": "2014-03-26",
  "publisher": "Health Level Seven International",
  "contact": [
    {
      "telecom": [
        {
          "system": "url",
          "value": "http://hl7.org"
        },
        {
          "system": "email",
          "value": "hq@HL7.org"
        }
      ]
    }
  ],
  "copyright": "This material derives from the HL7 Terminology THO. THO is copyright ©1989+ Health Level Seven International and is made available under the CC0 designation. For more licensing information see: https://terminology.hl7.org/license",
  "compose": {
    "include": [
      {
        "system": "https://fhir.kemkes.go.id/r4/CodeSystem/v3-ActCode",
        "filter": [
          {
            "property": "concept",
            "op": "is-a",
            "value": "_ObservationType"
          }
        ]
      },
      {
        "valueSet": [
          "https://fhir.kemkes.go.id/r4/ValueSet/v3-ObservationDiagnosisTypes"
        ]
      },
      {
        "valueSet": [
          "https://fhir.kemkes.go.id/r4/ValueSet/v3-LogicalObservationIdentifierNamesAndCodes"
        ]
      },
      {
        "valueSet": [
          "https://fhir.kemkes.go.id/r4/ValueSet/v3-ObservationSeriesType"
        ]
      },
      {
        "valueSet": [
          "https://fhir.kemkes.go.id/r4/ValueSet/v3-ObservationSequenceType"
        ]
      },
      {
        "valueSet": [
          "https://fhir.kemkes.go.id/r4/ValueSet/v3-AnnotationType"
        ]
      },
      {
        "valueSet": [
          "https://fhir.kemkes.go.id/r4/ValueSet/v3-ObservationIntoleranceType"
        ]
      },
      {
        "valueSet": [
          "https://fhir.kemkes.go.id/r4/ValueSet/v3-ObservationIssueTriggerCodedObservationType"
        ]
      },
      {
        "valueSet": [
          "https://fhir.kemkes.go.id/r4/ValueSet/v3-MedicationObservationType"
        ]
      },
      {
        "valueSet": [
          "https://fhir.kemkes.go.id/r4/ValueSet/v3-ObservationActContextAgeType"
        ]
      },
      {
        "valueSet": [
          "https://fhir.kemkes.go.id/r4/ValueSet/v3-GeneticObservationType"
        ]
      }
    ],
    "exclude": [
      {
        "system": "https://fhir.kemkes.go.id/r4/CodeSystem/v3-ActCode",
        "concept": [
          {
            "code": "_ObservationType"
          },
          {
            "code": "_ObservationIssueTriggerCodedObservationType"
          },
          {
            "code": "_GeneticObservationType"
          }
        ]
      }
    ]
  }
}
