{
  "resourceType": "ValueSet",
  "status": "draft",
  "name": "ClaimPayeeTypeCodes",
  "id": "payeetype",
  "title": "Payee Type Codes",
  "description": "Codes indicating the type of party to be reimbursed for cost of the products and service.",
  "url": "https://fhir.kemkes.go.id/r4/ValueSet/payeetype",
  "meta": {
    "lastUpdated": "2022-04-27T14:51:00.000+00:00",
    "profile": [
      "http://hl7.org/fhir/StructureDefinition/shareablevalueset"
    ]
  },
  "extension": [
    {
      "url": "http://hl7.org/fhir/StructureDefinition/structuredefinition-wg",
      "valueCode": "fm"
    },
    {
      "url": "http://hl7.org/fhir/StructureDefinition/structuredefinition-fmm",
      "valueInteger": 1
    }
  ],
  "identifier": [
    {
      "system": "urn:ietf:rfc:3986",
      "value": "urn:oid:2.16.840.1.113883.4.642.3.31"
    }
  ],
  "version": "1.0.0",
  "experimental": false,
  "date": "2022-04-27T14:51:00+00:00",
  "publisher": "Health Level Seven International",
  "contact": [
    {
      "telecom": [
        {
          "system": "url",
          "value": "http://hl7.org"
        },
        {
          "system": "email",
          "value": "hq@HL7.org"
        }
      ]
    }
  ],
  "immutable": true,
  "copyright": "This material derives from the HL7 Terminology THO. THO is copyright ©1989+ Health Level Seven International and is made available under the CC0 designation. For more licensing information see: https://terminology.hl7.org/license",
  "compose": {
    "include": [
      {
        "system": "https://fhir.kemkes.go.id/r4/CodeSystem/payeetype"
      }
    ]
  }
}
