<?xml version="1.0" encoding="UTF-8"?>

<CodeSystem xmlns="http://hl7.org/fhir">
  <id value="v3-mdc"/>
  <text>
    <status value="generated"/><div xmlns="http://www.w3.org/1999/xhtml"><p>This case-sensitive code system <code>urn:iso:std:iso:11073:10101</code> defines codes, but no codes are represented here</p></div>
  </text>
  <url value="urn:iso:std:iso:11073:10101"/>
  <identifier>
    <system value="urn:ietf:rfc:3986"/>
    <value value="urn:oid:2.16.840.1.113883.6.24"/>
  </identifier>
  <version value="0.1.0"/>
  <name value="Mdc"/>
  <title value="ISO 11073-10101 Health informatics - Point-of-care"/>
  <status value="active"/>
  <experimental value="false"/>
  <date value="2019-03-20T00:00:00-04:00"/>
  <publisher value="SatuSehat"/>
  <contact>
    <name value="SatuSehat"/>
    <telecom>
      <system value="url"/>
      <value value="https://satusehat.kemkes.go.id/"/>
    </telecom>
    <telecom>
      <system value="email"/>
      <value value="fhir@dto.kemkes.go.id"/>
    </telecom>
  </contact>
  <description value="The nomenclature relates primarily to vital signs monitoring, but also includes semantics of other medical devices that are commonly used in acute care settings. There are multiple coding partitions each of which has a systematic name consisting of a set of base concepts and differentiating criteria."/>
  <caseSensitive value="true"/>
  <content value="not-present"/>
</CodeSystem>